odoo/addons/account_fiscal_position_autodetect_optional_vies/README.rst
odoo/addons/account_fiscal_position_autodetect_optional_vies/__init__.py
odoo/addons/account_fiscal_position_autodetect_optional_vies/__manifest__.py
odoo/addons/account_fiscal_position_autodetect_optional_vies/i18n/account_fiscal_position_autodetect_optional_vies.pot
odoo/addons/account_fiscal_position_autodetect_optional_vies/i18n/it.po
odoo/addons/account_fiscal_position_autodetect_optional_vies/models/__init__.py
odoo/addons/account_fiscal_position_autodetect_optional_vies/models/account_fiscal_position.py
odoo/addons/account_fiscal_position_autodetect_optional_vies/readme/CONFIGURE.md
odoo/addons/account_fiscal_position_autodetect_optional_vies/readme/CONTRIBUTORS.md
odoo/addons/account_fiscal_position_autodetect_optional_vies/readme/DESCRIPTION.md
odoo/addons/account_fiscal_position_autodetect_optional_vies/readme/USAGE.md
odoo/addons/account_fiscal_position_autodetect_optional_vies/static/description/icon.png
odoo/addons/account_fiscal_position_autodetect_optional_vies/static/description/index.html
odoo/addons/account_fiscal_position_autodetect_optional_vies/tests/__init__.py
odoo/addons/account_fiscal_position_autodetect_optional_vies/tests/test_account_fiscal_position_vies.py
odoo/addons/account_fiscal_position_autodetect_optional_vies/views/account_fiscal_position_view.xml
odoo_addon_account_fiscal_position_autodetect_optional_vies-17.0.1.0.0.4.dist-info/METADATA
odoo_addon_account_fiscal_position_autodetect_optional_vies-17.0.1.0.0.4.dist-info/WHEEL
odoo_addon_account_fiscal_position_autodetect_optional_vies-17.0.1.0.0.4.dist-info/top_level.txt
odoo_addon_account_fiscal_position_autodetect_optional_vies-17.0.1.0.0.4.dist-info/RECORD
